freezehelper/__init__.py
freezehelper/helpers.py
freezehelper-2.0.0.dist-info/COPYING
freezehelper-2.0.0.dist-info/COPYING.LESSER
freezehelper-2.0.0.dist-info/LICENSE
freezehelper-2.0.0.dist-info/METADATA
freezehelper-2.0.0.dist-info/WHEEL
freezehelper-2.0.0.dist-info/top_level.txt
freezehelper-2.0.0.dist-info/RECORD
