Metadata-Version: 2.1
Name: freezehelper
Version: 2.0.0
Summary: A Python package to simplify checks for frozen state and executable directory
Home-page: https://github.com/brandonmpace/freezehelper
Author: Brandon M. Pace
Author-email: brandonmpace@gmail.com
License: GNU Lesser General Public License v3 or later
Keywords: freeze frozen PyInstaller parent child process executable directory path
Platform: any
Classifier: Development Status :: 5 - Production/Stable
Classifier: License :: OSI Approved :: GNU Lesser General Public License v3 or later (LGPLv3+)
Classifier: Operating System :: OS Independent
Classifier: Programming Language :: Python :: 3
Requires-Python: >=3.6.5
